__init__.py
tkdev/__init__.py
tkdev/__main__.py
tkdev/devcore/__init__.py
tkdev/devdemo/__init__.py
tkdev/devicon/__init__.py
tkdev/devresize/__init__.py
tkinterDev-2.0.4.dist-info/LICENSE
tkinterDev-2.0.4.dist-info/METADATA
tkinterDev-2.0.4.dist-info/WHEEL
tkinterDev-2.0.4.dist-info/top_level.txt
tkinterDev-2.0.4.dist-info/RECORD
