Metadata-Version: 2.1
Name: tkinterDev
Version: 2.0.4
Summary: tkinter Tool
Home-page: https://xiangqinxidevelopment.jetbrains.space/p/tkinterdev
Author: XiangQinxi
Author-email: XiangQinxi@outlook.com
Classifier: Programming Language :: Python :: 3
Classifier: License :: OSI Approved :: MIT License
Classifier: Operating System :: OS Independent
License-File: LICENSE
